otdr_reader/__init__.py
otdr_reader/classes.py
otdr_reader/helpers.py
otdr_reader/logo/cohaerentia.png
otdr_reader/main.py
otdr_reader/plotter.py
otdr_reader-1.3.0.dist-info/entry_points.txt
otdr_reader-1.3.0.dist-info/METADATA
otdr_reader-1.3.0.dist-info/WHEEL
otdr_reader-1.3.0.dist-info/RECORD
