Metadata-Version: 2.3
Name: otdr-reader
Version: 1.3.0
Summary: Module to convert .sor otdr files to json or html plot.
Author: Marco Brunero
Author-email: marco.brunero@cohaerentia.com
Requires-Python: >=3.12,<4.0
Classifier: Programming Language :: Python :: 3
Classifier: Programming Language :: Python :: 3.12
Classifier: Programming Language :: Python :: 3.13
Requires-Dist: ipywidgets (>=8.1.2,<9.0.0)
Requires-Dist: jsonpickle (>=3.0.3,<4.0.0)
Requires-Dist: nbformat (>=5.9.2,<6.0.0)
Requires-Dist: numpy (>=2.3.4,<3.0.0)
Requires-Dist: plotly (>=5.19.0,<6.0.0)
Requires-Dist: pyotdr (>=2.1.1,<3.0.0)
Requires-Dist: typer[all] (>=0.9.0,<0.10.0)
